.bandit
.checks.yml
.travis.yml
LICENSE
README.md
requirements.txt
setup.cfg
setup.py
enet/__init__.py
enet/base.py
enet/exceptions.py
enet/live.py
enet/test.py
enet/types.py
enetpy.egg-info/PKG-INFO
enetpy.egg-info/SOURCES.txt
enetpy.egg-info/dependency_links.txt
enetpy.egg-info/not-zip-safe
enetpy.egg-info/pbr.json
enetpy.egg-info/requires.txt
enetpy.egg-info/top_level.txt
tests/__init__.py
tests/conftest.py
tests/test_api.py