Metadata-Version: 2.1
Name: enetpy
Version: 1.0.1
Summary: Python wrapper for the enet Marktpartner API
Home-page: https://github.com/Thermondo/python-enet
Author: Thermondo GmbH
Author-email: opensource@thermondo.com
License: Apache-2
Project-URL: Bug Tracker, https://github.com/Thermondo/python-enet/issues
Project-URL: Documentation, https://github.com/Thermondo/python-enet
Project-URL: Source Code, https://github.com/Thermondo/python-enet
Keywords: api
Platform: UNKNOWN
Classifier: Development Status :: 5 - Production/Stable
Classifier: Environment :: Web Environment
Classifier: Intended Audience :: Developers
Classifier: License :: OSI Approved :: Apache Software License
Classifier: Operating System :: OS Independent
Classifier: Programming Language :: Python
Classifier: Programming Language :: Python :: 3
